report_creator/__init__.py
report_creator/__version__.py
report_creator/base.py
report_creator/charts.py
report_creator/report_creator.py
report_creator/theming.py
report_creator/utilities.py
report_creator/templates/default.html
report_creator-1.1.3.dist-info/licenses/LICENSE
report_creator-1.1.3.dist-info/METADATA
report_creator-1.1.3.dist-info/WHEEL
report_creator-1.1.3.dist-info/top_level.txt
report_creator-1.1.3.dist-info/RECORD
