Metadata-Version: 2.4
Name: report_creator
Version: 1.1.3
Summary: Create self-contained HTML reports from Python.
Home-page: https://github.com/darenr/report_creator
Author: Daren Race
Author-email: daren.race@gmail.com
Maintainer: Daren Race
Maintainer-email: daren.race@gmail.com
License: MIT
Keywords: python,html,reports,report,creator,generator,markdown,yaml,plot,chart,table,blog
Classifier: License :: OSI Approved :: MIT License
Classifier: Operating System :: OS Independent
Classifier: Intended Audience :: Developers
Classifier: Programming Language :: Python
Classifier: Programming Language :: Python :: 3.10
Classifier: Programming Language :: Python :: 3.11
Classifier: Programming Language :: Python :: 3.12
Classifier: Programming Language :: Python :: 3.13
Classifier: Programming Language :: Python :: 3.14
Classifier: Programming Language :: Python :: Implementation :: CPython
Classifier: Programming Language :: Python :: Implementation :: PyPy
Requires-Python: >=3.9
License-File: LICENSE
Requires-Dist: pandas
Requires-Dist: pyarrow
Requires-Dist: numpy
Requires-Dist: matplotlib
Requires-Dist: mistune>=3.0.2
Requires-Dist: pyyaml
Requires-Dist: plotly
Requires-Dist: plotly-express
Requires-Dist: Jinja2
Requires-Dist: humanize
Requires-Dist: beautifulsoup4
Requires-Dist: python-dateutil
Requires-Dist: requests
Requires-Dist: pillow
Requires-Dist: md4mathjax
Requires-Dist: emoji
Requires-Dist: setuptools
Requires-Dist: tabulate
Requires-Dist: loguru
Requires-Dist: rich
Dynamic: author
Dynamic: author-email
Dynamic: classifier
Dynamic: description
Dynamic: description-content-type
Dynamic: home-page
Dynamic: keywords
Dynamic: license
Dynamic: license-file
Dynamic: maintainer
Dynamic: maintainer-email
Dynamic: requires-dist
Dynamic: requires-python
Dynamic: summary
